osc_openapi_framework/__init__.py
osc_openapi_framework/analyzer.py
osc_openapi_framework/builder.py
osc_openapi_framework/parser.py
osc_openapi_framework/schema.py
osc_openapi_framework-0.0.1.dist-info/LICENSE
osc_openapi_framework-0.0.1.dist-info/METADATA
osc_openapi_framework-0.0.1.dist-info/WHEEL
osc_openapi_framework-0.0.1.dist-info/top_level.txt
osc_openapi_framework-0.0.1.dist-info/RECORD
