Metadata-Version: 2.1
Name: osc-openapi-framework
Version: 0.0.1
Summary: Framework to build/parse OpenAPI
Home-page: https://github.com/outscale/osc_openapi_framework
Author: Outscal SAS
Author-email: opensource@outscale.com
License: BSD
Platform: UNKNOWN
Classifier: License :: OSI Approved :: BSD License
Classifier: Programming Language :: Python :: 3
Classifier: Programming Language :: Python :: 3.6
Classifier: Programming Language :: Python :: 3.7
Classifier: Programming Language :: Python :: 3.8
Classifier: Programming Language :: Python :: 3.9
Classifier: Operating System :: OS Independent
Requires-Dist: openapi-spec-validator
Requires-Dist: prance
